<?xml version="1.0" encoding="utf-8" ?>
<dwsync>
<file name="promocion.sql.zip" server="192.168.1.1//var/www/html/prom/" local="130143455800000000" remote="130143455800000000" Dst="0" />
<file name="pagination.php" server="192.168.1.1//var/www/html/prom/" local="130143455800000000" remote="130143455800000000" Dst="0" />
<file name="cerrar.php" server="192.168.1.1//var/www/html/prom/" local="130143455800000000" remote="130143455800000000" Dst="0" />
<file name="cerrarsesion.php" server="192.168.1.1//var/www/html/prom/" local="130143455800000000" remote="130143455800000000" Dst="0" />
<file name="existeconexion2.php" server="192.168.1.1//var/www/html/prom/" local="130143455800000000" remote="130143455800000000" Dst="0" />
<file name="index.php" server="192.168.1.1//var/www/html/prom/" local="130143455800000000" remote="130143455800000000" Dst="0" />
<file name="config.php" server="192.168.1.1//var/www/html/prom/" local="130144349560000000" remote="130144349560000000" Dst="0" />
<file name="existeconexion.php" server="192.168.1.1//var/www/html/prom/" local="130143455800000000" remote="130143455800000000" Dst="0" />
<file name="promocionND.sql.zip" server="192.168.1.1//var/www/html/prom/" local="130143455800000000" remote="130143455800000000" Dst="0" />
</dwsync>